ejercicios/Guia1/Ejercicio4/Fuentes/sumNb.vhd
library IEEE;
use IEEE.std_logic_1164.all;
use IEEE.numeric_std.all;


--sumador sin signo generico de N bits.
entity sumNb is
	generic( N: natural := 4);
	port(
		a_i: 	in std_logic_vector(N-1 downto 0);
		b_i: 	in std_logic_vector(N-1 downto 0);
		ci_i: 	in std_logic;
		s_o: 	out std_logic_vector(N-1 downto 0);
		co_o: 	out std_logic
	);
end;


architecture sumNb_arq of sumNb is
	signal res: std_logic_vector(N+1 downto 0);
begin
	res 	<= std_logic_vector(unsigned('0' & a_i & ci_i) + unsigned('0' & b_i & '1'));
	s_o		<= res(N downto 1);
	co_o 	<= res(N+1);
end sumNb_arq;

multiplicador/Fuentes/regNb.vhd
library IEEE;
use IEEE.std_logic_1164.all;

entity regNb is
	generic(
		N: natural := 4
	);
	port(
		D_i:	in	std_logic_vector(N-1 downto 0);
		rst_i:	in	std_logic;
		clk_i:	in	std_logic;
		Q_o:	out	std_logic_vector(N-1 downto 0)
	);
end;


architecture regNb_arq of regNb is
begin
	process(clk_i, rst_i)
     	begin
          if rst_i = '1' then
               Q_o <= (others => '0');
          elsif rising_edge(clk_i) then
                    Q_o <= D_i;
          end if;
     	end process;
end regNb_arq;

multiplicador/Fuentes/multiplicador.vhd
library IEEE;
use IEEE.std_logic_1164.all;


entity multiplicador is
	generic(
		N: natural := 4
	);
	port(
		clk_i    : in std_logic;
		load_i   : in std_logic;
		rst_i   : in std_logic;
		opA_i    : in std_logic_vector(N-1 downto 0);
		opB_i    : in std_logic_vector(N-1 downto 0);
		product_o: out std_logic_vector(2*N-1 downto 0)
	);
end;

architecture multiplicador_arq of multiplicador is
	--declaracion del mponente registro
	component regNb is
		generic(
			N: natural := 4
		);
		port(
			D_i:	in	std_logic_vector(N-1 downto 0);
			rst_i:	in	std_logic;
			clk_i:	in	std_logic;
			Q_o:	out	std_logic_vector(N-1 downto 0)
		);
	end component;
	
	--declaracion del componente sumador
	component sumNb is
		generic( 
			N: natural := 4
		);
		port(
			a_i: 	in std_logic_vector(N-1 downto 0);
			b_i: 	in std_logic_vector(N-1 downto 0);
			ci_i: 	in std_logic;
			s_o: 	out std_logic_vector(N-1 downto 0);
			co_o: 	out std_logic
		);
	end component;
	
	signal entP,entB,salP,salSum,salB,salA,aux: std_logic_vector(N-1 downto 0);
	signal co: std_logic;
begin	
	--instancia registro A
	regA_inst: regNb
		generic map(
			N => N		
		)
		port map(
			D_i   => opA_i,
			rst_i => '0',
			clk_i => clk_i,
			Q_o   => salA	
		);
		
	--instancia registro B
	regB_inst: regNb
		generic map(
			N => N
		)
		port map(
			D_i   => entB,
			rst_i => '0',
			clk_i => clk_i,
			Q_o   => salB
		);
	--instancia registro P
	regP_inst: regNb
		generic map(
			N => N		
		)
		port map(
			D_i   => entP,
			rst_i => load_i,
			clk_i => clk_i,
			Q_o   => salP
		);
		
	sum_inst: sumNb
		generic map(
			N => N		
		)
		port map(
			a_i  => salP,
			b_i  => aux,
			ci_i => '0',
			s_o  => salSum,
			co_o => co
		);
	entP <= co & salSum(N-1 downto 1);
	aux  <= salA  when salB(0) = '1' else (N-1 downto 0 => '0');
	entB <= opB_i when load_i = '1' else salSum(0) & salB(N-1 downto 1);
	product_o <= salP & salB; 
end multiplicador_arq;

multiplicador/Fuentes/multiplicador_tb.vhd
library IEEE;
use IEEE.std_logic_1164.all;
use IEEE.numeric_std.all;


entity multiplicador_tb is
end;

architecture multiplicador_tb_arq of multiplicador_tb is
	component multiplicador is
		generic(
			N: natural := 4
		);
		port(
			clk_i    : in std_logic;
			load_i   : in std_logic;
			rst_i    : in std_logic;
			opA_i    : in std_logic_vector(N-1 downto 0);
			opB_i    : in std_logic_vector(N-1 downto 0);
			product_o: out std_logic_vector(2*N-1 downto 0)
		);
	end component;
	
	constant N_tb : natural := 5; 
	signal clk_tb : std_logic := '0';
	signal load_tb: std_logic := '0';
	signal rst_tb : std_logic := '1';
	signal opA_tb : std_logic_vector(N_tb-1 downto 0) := "00011";
	signal opB_tb : std_logic_vector(N_tb-1 downto 0) := std_logic_vector(to_unsigned(0,N_tb));
	signal product_tb: std_logic_vector(2*N_tb-1 downto 0);
begin
	clk_tb  <= not clk_tb after 10 ns;
	rst_tb  <= '0' after 20 ns;
 	
 	load_tb <= '1' after 100 ns, '0' after 120 ns;
	opB_tb  <= std_logic_vector(to_unsigned(6,N_tb)) after 100 ns;
	
	DUT: multiplicador
		generic map(
			N => N_tb
		)
		port map(
			clk_i     => clk_tb,
			load_i    => load_tb,
			rst_i     => rst_tb,
			opA_i     => opA_tb,
			opB_i     => opB_tb,
			product_o => product_tb
		);
end multiplicador_tb_arq;

multiplicador/Simulacion/out/mult_tb.vcd
$date
  Tue Dec 29 14:53:46 2020
$end
$version
  GHDL v0
$end
$timescale
  1 fs
$end
$scope module standard $end
$upscope $end
$scope module std_logic_1164 $end
$upscope $end
$scope module numeric_std $end
$upscope $end
$scope module multiplicador_tb $end
$var reg 1 ! clk_tb $end
$var reg 1 " load_tb $end
$var reg 1 # rst_tb $end
$var reg 5 $ opa_tb[4:0] $end
$var reg 5 % opb_tb[4:0] $end
$var reg 10 & product_tb[9:0] $end
$scope module dut $end
$var reg 1 ' clk_i $end
$var reg 1 ( load_i $end
$var reg 1 ) rst_i $end
$var reg 5 * opa_i[4:0] $end
$var reg 5 + opb_i[4:0] $end
$var reg 10 , product_o[9:0] $end
$var reg 5 - entp[4:0] $end
$var reg 5 . entb[4:0] $end
$var reg 5 / salp[4:0] $end
$var reg 5 0 salsum[4:0] $end
$var reg 5 1 salb[4:0] $end
$var reg 5 2 sala[4:0] $end
$var reg 5 3 aux[4:0] $end
$var reg 1 4 co $end
$scope module rega_inst $end
$var reg 5 5 d_i[4:0] $end
$var reg 1 6 rst_i $end
$var reg 1 7 clk_i $end
$var reg 5 8 q_o[4:0] $end
$upscope $end
$scope module regb_inst $end
$var reg 5 9 d_i[4:0] $end
$var reg 1 : rst_i $end
$var reg 1 ; clk_i $end
$var reg 5 < q_o[4:0] $end
$upscope $end
$scope module regp_inst $end
$var reg 5 = d_i[4:0] $end
$var reg 1 > rst_i $end
$var reg 1 ? clk_i $end
$var reg 5 @ q_o[4:0] $end
$upscope $end
$scope module sum_inst $end
$var reg 5 A a_i[4:0] $end
$var reg 5 B b_i[4:0] $end
$var reg 1 C ci_i $end
$var reg 5 D s_o[4:0] $end
$var reg 1 E co_o $end
$var reg 7 F res[6:0] $end
$upscope $end
$upscope $end
$upscope $end
$enddefinitions $end
#0
0!
0"
1#
b00011 $
b00000 %
bUUUUUUUUUU &
0'
0(
1)
b00011 *
b00000 +
bUUUUUUUUUU ,
bXXXXX -
bXUUUU .
bUUUUU /
bXXXXX 0
bUUUUU 1
bUUUUU 2
b00000 3
X4
b00011 5
06
07
bUUUUU 8
bXUUUU 9
0:
0;
bUUUUU <
bXXXXX =
0>
0?
bUUUUU @
bUUUUU A
b00000 B
0C
bXXXXX D
XE
bXXXXXXX F
#10000000
1!
bXXXXXXUUUU &
1'
bXXXXXXUUUU ,
bXXUUU .
bXXXXX /
bXUUUU 1
b00011 2
17
b00011 8
bXXUUU 9
1;
bXUUUU <
1?
bXXXXX @
bXXXXX A
#20000000
0!
0#
0'
0)
07
0;
0?
#30000000
1!
bXXXXXXXUUU &
1'
bXXXXXXXUUU ,
bXXXUU .
bXXUUU 1
17
bXXXUU 9
1;
bXXUUU <
1?
#40000000
0!
0'
07
0;
0?
#50000000
1!
bXXXXXXXXUU &
1'
bXXXXXXXXUU ,
bXXXXU .
bXXXUU 1
17
bXXXXU 9
1;
bXXXUU <
1?
#60000000
0!
0'
07
0;
0?
#70000000
1!
bXXXXXXXXXU &
1'
bXXXXXXXXXU ,
bXXXXX .
bXXXXU 1
17
bXXXXX 9
1;
bXXXXU <
1?
#80000000
0!
0'
07
0;
0?
#90000000
1!
bXXXXXXXXXX &
1'
bXXXXXXXXXX ,
bXXXXX 1
17
1;
bXXXXX <
1?
#100000000
0!
1"
b00110 %
b00000XXXXX &
0'
1(
b00110 +
b00000XXXXX ,
b00000 -
b00110 .
b00000 /
b00000 0
04
07
b00110 9
0;
b00000 =
1>
0?
b00000 @
b00000 A
b00000 D
0E
b0000001 F
#110000000
1!
b0000000110 &
1'
b0000000110 ,
b00110 1
17
1;
b00110 <
1?
#120000000
0!
0"
0'
0(
b00011 .
07
b00011 9
0;
0>
0?
#130000000
1!
b0000000011 &
1'
b0000000011 ,
b00001 -
b10001 .
b00011 0
b00011 1
b00011 3
17
b10001 9
1;
b00011 <
b00001 =
1?
b00011 B
b00011 D
b0000111 F
#140000000
0!
0'
07
0;
0?
#150000000
1!
b0000110001 &
1'
b0000110001 ,
b00010 -
b01000 .
b00001 /
b00100 0
b10001 1
17
b01000 9
1;
b10001 <
b00010 =
1?
b00001 @
b00001 A
b00100 D
b0001001 F
#160000000
0!
0'
07
0;
0?
#170000000
1!
b0001001000 &
1'
b0001001000 ,
b00001 -
b00100 .
b00010 /
b00010 0
b01000 1
b00000 3
17
b00100 9
1;
b01000 <
b00001 =
1?
b00010 @
b00010 A
b00000 B
b00010 D
b0000101 F
#180000000
0!
0'
07
0;
0?
#190000000
1!
b0000100100 &
1'
b0000100100 ,
b00000 -
b10010 .
b00001 /
b00001 0
b00100 1
17
b10010 9
1;
b00100 <
b00000 =
1?
b00001 @
b00001 A
b00001 D
b0000011 F
#200000000
0!
0'
07
0;
0?
#210000000
1!
b0000010010 &
1'
b0000010010 ,
b01001 .
b00000 /
b00000 0
b10010 1
17
b01001 9
1;
b10010 <
1?
b00000 @
b00000 A
b00000 D
b0000001 F
#220000000
0!
0'
07
0;
0?
#230000000
1!
b0000001001 &
1'
b0000001001 ,
b00001 -
b10100 .
b00011 0
b01001 1
b00011 3
17
b10100 9
1;
b01001 <
b00001 =
1?
b00011 B
b00011 D
b0000111 F
#240000000
0!
0'
07
0;
0?
#250000000
1!
b0000110100 &
1'
b0000110100 ,
b00000 -
b11010 .
b00001 /
b00001 0
b10100 1
b00000 3
17
b11010 9
1;
b10100 <
b00000 =
1?
b00001 @
b00001 A
b00000 B
b00001 D
b0000011 F
#260000000
0!
0'
07
0;
0?
#270000000
1!
b0000011010 &
1'
b0000011010 ,
b01101 .
b00000 /
b00000 0
b11010 1
17
b01101 9
1;
b11010 <
1?
b00000 @
b00000 A
b00000 D
b0000001 F
#280000000
0!
0'
07
0;
0?
#290000000
1!
b0000001101 &
1'
b0000001101 ,
b00001 -
b10110 .
b00011 0
b01101 1
b00011 3
17
b10110 9
1;
b01101 <
b00001 =
1?
b00011 B
b00011 D
b0000111 F
