ejercicios/Guia1/Ejercicio4/Fuentes/sumNb.vhd
library IEEE;
use IEEE.std_logic_1164.all;
use IEEE.numeric_std.all;


--sumador sin signo generico de N bits.
entity sumNb is
	generic( N: natural := 4);
	port(
		a_i: 	in std_logic_vector(N-1 downto 0);
		b_i: 	in std_logic_vector(N-1 downto 0);
		ci_i: 	in std_logic;
		s_o: 	out std_logic_vector(N-1 downto 0);
		co_o: 	out std_logic
	);
end;


architecture sumNb_arq of sumNb is
	signal res: std_logic_vector(N+1 downto 0);
begin
	res 	<= std_logic_vector(unsigned('0' & a_i & ci_i) + unsigned('0' & b_i & '1'));
	s_o		<= res(N downto 1);
	co_o 	<= res(N+1);
end sumNb_arq;

tps/tp6-final/Fuentes/regNb.vhd
library IEEE;
use IEEE.std_logic_1164.all;

entity regNb is
	generic(
		N: natural := 4
	);
	port(
		D_i:	in	std_logic_vector(N-1 downto 0);
		rst_i:	in	std_logic;
		ena_i:	in 	std_logic;
		clk_i:	in	std_logic;
		Q_o:	out	std_logic_vector(N-1 downto 0)
	);
end;


architecture regNb_arq of regNb is
begin
	process(clk_i, rst_i)
     	begin
          if rst_i = '1' then
               Q_o <= (others => '0');
          elsif rising_edge(clk_i) then
          	if ena_i = '1' then
                    Q_o <= D_i;
         	end if;
          end if;
     	end process;
end regNb_arq;

tps/tp6-final/multiplicador/Fuentes/multiplicador.vhd
library IEEE;
use IEEE.std_logic_1164.all;


entity multiplicador is
	generic(
		N: natural := 4
	);
	port(
		clk_i    : in std_logic;
		load_i   : in std_logic;
		opA_i    : in std_logic_vector(N-1 downto 0);
		opB_i    : in std_logic_vector(N-1 downto 0);
		done_o   : out std_logic;
		product_o: out std_logic_vector(2*N-1 downto 0)
	);
end;

architecture multiplicador_arq of multiplicador is
	--declaracion del mponente registro
	component regNb is
		generic(
			N: natural := 4
		);
		port(
			D_i:	in	std_logic_vector(N-1 downto 0);
			rst_i:	in	std_logic;
			ena_i:	in 	std_logic;
			clk_i:	in	std_logic;
			Q_o:	out	std_logic_vector(N-1 downto 0)
		);
	end component;
	
	--declaracion del componente sumador
	component sumNb is
		generic( 
			N: natural := 4
		);
		port(
			a_i: 	in std_logic_vector(N-1 downto 0);
			b_i: 	in std_logic_vector(N-1 downto 0);
			ci_i: 	in std_logic;
			s_o: 	out std_logic_vector(N-1 downto 0);
			co_o: 	out std_logic
		);
	end component;
	signal entP,entB,salP,salSum,salB,salA,aux: std_logic_vector(N-1 downto 0);
	signal co: std_logic;
	signal enaRegP,enaRegB: std_logic;
begin
	process(clk_i,load_i) is
		variable counter: natural;
	begin
		if load_i = '1' then
			enaRegP <= '1';	
			enaRegB <= '1';
			done_o <= '0';
			counter := 0;
		elsif rising_edge(clk_i) then
			if counter = N-1  then
				enaRegP <= '0';
				enaRegB <= '0';
				done_o <= '1';
			else
				counter := counter + 1;
			end if;
		end if;
	end process;
	
	--instancia registro A
	regA_inst: regNb
		generic map(
			N => N		
		)
		port map(
			D_i   => opA_i,
			ena_i => '1',
			rst_i => '0',
			clk_i => clk_i,
			Q_o   => salA	
		);
		
	--instancia registro B
	regB_inst: regNb
		generic map(
			N => N
		)
		port map(
			D_i   => entB,
			ena_i => enaRegB,
			rst_i => '0',
			clk_i => clk_i,
			Q_o   => salB
		);
	--instancia registro P
	regP_inst: regNb
		generic map(
			N => N		
		)
		port map(
			D_i   => entP,
			ena_i => enaRegP,
			rst_i => load_i,
			clk_i => clk_i,
			Q_o   => salP
		);
		
	sum_inst: sumNb
		generic map(
			N => N		
		)
		port map(
			a_i  => salP,
			b_i  => aux,
			ci_i => '0',
			s_o  => salSum,
			co_o => co
		);
	entP <= co & salSum(N-1 downto 1);
	aux  <= salA  when (salB(0) = '1' and load_i = '0') else (N-1 downto 0 => '0');
	entB <= opB_i when load_i = '1' else salSum(0) & salB(N-1 downto 1);
	product_o <= salP & salB; 
end multiplicador_arq;

tps/tp6-final/multiplicador/Fuentes/multiplicador_tb.vhd
library IEEE;
use IEEE.std_logic_1164.all;
use IEEE.numeric_std.all;


entity multiplicador_tb is
end;

architecture multiplicador_tb_arq of multiplicador_tb is
	component multiplicador is
		generic(
			N: natural := 4
		);
		port(
			clk_i    : in std_logic;
			load_i   : in std_logic;
			opA_i    : in std_logic_vector(N-1 downto 0);
			opB_i    : in std_logic_vector(N-1 downto 0);
			done_o   : out std_logic;
			product_o: out std_logic_vector(2*N-1 downto 0)
		);
	end component;

	constant SIM_TIME_NS : time := 800 ns;

	constant N_tb : natural := 5; 
	signal clk_tb : std_logic := '0';
	signal load_tb: std_logic := '0';
	signal rst_tb : std_logic := '1';
	signal opA_tb : std_logic_vector(N_tb-1 downto 0) := std_logic_vector(to_unsigned(3,N_tb));
	signal opB_tb : std_logic_vector(N_tb-1 downto 0) := std_logic_vector(to_unsigned(0,N_tb));
	signal product_tb: std_logic_vector(2*N_tb-1 downto 0);
	signal done_tb : std_logic;
begin
	clk_tb  <= not clk_tb after 10 ns;
	rst_tb  <= '0' after 20 ns;
 	
 	load_tb <= '1' after 100 ns, '0' after 120 ns,'1' after 460 ns, '0' after 480 ns;
	opB_tb  <= std_logic_vector(to_unsigned(6,N_tb)) after 100 ns,std_logic_vector(to_unsigned(3,N_tb)) after 460 ns;
	
	DUT: multiplicador
		generic map(
			N => N_tb
		)
		port map(
			clk_i 		=> clk_tb,
			load_i		=> load_tb,
			opA_i 		=> opA_tb,
			opB_i 		=> opB_tb,
			done_o		=> done_tb,
			product_o	=> product_tb
		);


	stop_simulation : process
		begin
			wait for SIM_TIME_NS; --run the simulation for this duration
			assert false
			report "Simulation finished."
			severity failure;
		end process;
end multiplicador_tb_arq;

multiplicador/Fuentes/multiplicador_tb.vcd
$date
  Sun Jan  3 23:41:44 2021
$end
$version
  GHDL v0
$end
$timescale
  1 fs
$end
$scope module standard $end
$upscope $end
$scope module std_logic_1164 $end
$upscope $end
$scope module numeric_std $end
$upscope $end
$scope module multiplicador_tb $end
$var reg 1 ! clk_tb $end
$var reg 1 " load_tb $end
$var reg 1 # rst_tb $end
$var reg 5 $ opa_tb[4:0] $end
$var reg 5 % opb_tb[4:0] $end
$var reg 10 & product_tb[9:0] $end
$var reg 1 ' done_tb $end
$scope module dut $end
$var reg 1 ( clk_i $end
$var reg 1 ) load_i $end
$var reg 5 * opa_i[4:0] $end
$var reg 5 + opb_i[4:0] $end
$var reg 1 , done_o $end
$var reg 10 - product_o[9:0] $end
$var reg 5 . entp[4:0] $end
$var reg 5 / entb[4:0] $end
$var reg 5 0 salp[4:0] $end
$var reg 5 1 salsum[4:0] $end
$var reg 5 2 salb[4:0] $end
$var reg 5 3 sala[4:0] $end
$var reg 5 4 aux[4:0] $end
$var reg 1 5 co $end
$var reg 1 6 enaregp $end
$var reg 1 7 enaregb $end
$scope module rega_inst $end
$var reg 5 8 d_i[4:0] $end
$var reg 1 9 rst_i $end
$var reg 1 : ena_i $end
$var reg 1 ; clk_i $end
$var reg 5 < q_o[4:0] $end
$upscope $end
$scope module regb_inst $end
$var reg 5 = d_i[4:0] $end
$var reg 1 > rst_i $end
$var reg 1 ? ena_i $end
$var reg 1 @ clk_i $end
$var reg 5 A q_o[4:0] $end
$upscope $end
$scope module regp_inst $end
$var reg 5 B d_i[4:0] $end
$var reg 1 C rst_i $end
$var reg 1 D ena_i $end
$var reg 1 E clk_i $end
$var reg 5 F q_o[4:0] $end
$upscope $end
$scope module sum_inst $end
$var reg 5 G a_i[4:0] $end
$var reg 5 H b_i[4:0] $end
$var reg 1 I ci_i $end
$var reg 5 J s_o[4:0] $end
$var reg 1 K co_o $end
$var reg 7 L res[6:0] $end
$upscope $end
$upscope $end
$upscope $end
$enddefinitions $end
#0
0!
0"
1#
b00011 $
b00000 %
bUUUUUUUUUU &
U'
0(
0)
b00011 *
b00000 +
U,
bUUUUUUUUUU -
bXXXXX .
bXUUUU /
bUUUUU 0
bXXXXX 1
bUUUUU 2
bUUUUU 3
b00000 4
X5
U6
U7
b00011 8
09
1:
0;
bUUUUU <
bXUUUU =
0>
U?
0@
bUUUUU A
bXXXXX B
0C
UD
0E
bUUUUU F
bUUUUU G
b00000 H
0I
bXXXXX J
XK
bXXXXXXX L
#10000000
1!
1(
b00011 3
1;
b00011 <
1@
1E
#20000000
0!
0#
0(
0;
0@
0E
#30000000
1!
1(
1;
1@
1E
#40000000
0!
0(
0;
0@
0E
#50000000
1!
1(
1;
1@
1E
#60000000
0!
0(
0;
0@
0E
#70000000
1!
1(
1;
1@
1E
#80000000
0!
0(
0;
0@
0E
#90000000
1!
1'
1(
1,
06
07
1;
0?
1@
0D
1E
#100000000
0!
1"
b00110 %
b00000UUUUU &
0'
0(
1)
b00110 +
0,
b00000UUUUU -
b00000 .
b00110 /
b00000 0
b00000 1
05
16
17
0;
b00110 =
1?
0@
b00000 B
1C
1D
0E
b00000 F
b00000 G
b00000 J
0K
b0000001 L
#110000000
1!
b0000000110 &
1(
b0000000110 -
b00110 2
1;
1@
b00110 A
1E
#120000000
0!
0"
0(
0)
b00011 /
0;
b00011 =
0@
0C
0E
#130000000
1!
b0000000011 &
1(
b0000000011 -
b00001 .
b10001 /
b00011 1
b00011 2
b00011 4
1;
b10001 =
1@
b00011 A
b00001 B
1E
b00011 H
b00011 J
b0000111 L
#140000000
0!
0(
0;
0@
0E
#150000000
1!
b0000110001 &
1(
b0000110001 -
b00010 .
b01000 /
b00001 0
b00100 1
b10001 2
1;
b01000 =
1@
b10001 A
b00010 B
1E
b00001 F
b00001 G
b00100 J
b0001001 L
#160000000
0!
0(
0;
0@
0E
#170000000
1!
b0001001000 &
1(
b0001001000 -
b00001 .
b00100 /
b00010 0
b00010 1
b01000 2
b00000 4
1;
b00100 =
1@
b01000 A
b00001 B
1E
b00010 F
b00010 G
b00000 H
b00010 J
b0000101 L
#180000000
0!
0(
0;
0@
0E
#190000000
1!
b0000100100 &
1(
b0000100100 -
b00000 .
b10010 /
b00001 0
b00001 1
b00100 2
1;
b10010 =
1@
b00100 A
b00000 B
1E
b00001 F
b00001 G
b00001 J
b0000011 L
#200000000
0!
0(
0;
0@
0E
#210000000
1!
b0000010010 &
1'
1(
1,
b0000010010 -
b01001 /
b00000 0
b00000 1
b10010 2
06
07
1;
b01001 =
0?
1@
b10010 A
0D
1E
b00000 F
b00000 G
b00000 J
b0000001 L
#220000000
0!
0(
0;
0@
0E
#230000000
1!
1(
1;
1@
1E
#240000000
0!
0(
0;
0@
0E
#250000000
1!
1(
1;
1@
1E
#260000000
0!
0(
0;
0@
0E
#270000000
1!
1(
1;
1@
1E
#280000000
0!
0(
0;
0@
0E
#290000000
1!
1(
1;
1@
1E
#300000000
0!
0(
0;
0@
0E
#310000000
1!
1(
1;
1@
1E
#320000000
0!
0(
0;
0@
0E
#330000000
1!
1(
1;
1@
1E
#340000000
0!
0(
0;
0@
0E
#350000000
1!
1(
1;
1@
1E
#360000000
0!
0(
0;
0@
0E
#370000000
1!
1(
1;
1@
1E
#380000000
0!
0(
0;
0@
0E
#390000000
1!
1(
1;
1@
1E
#400000000
0!
0(
0;
0@
0E
#410000000
1!
1(
1;
1@
1E
#420000000
0!
0(
0;
0@
0E
#430000000
1!
1(
1;
1@
1E
#440000000
0!
0(
0;
0@
0E
#450000000
1!
1(
1;
1@
1E
#460000000
0!
1"
b00011 %
0'
0(
1)
b00011 +
0,
b00011 /
16
17
0;
b00011 =
1?
0@
1C
1D
0E
#470000000
1!
b0000000011 &
1(
b0000000011 -
b00011 2
1;
1@
b00011 A
1E
#480000000
0!
0"
0(
0)
b00001 .
b10001 /
b00011 1
b00011 4
0;
b10001 =
0@
b00001 B
0C
0E
b00011 H
b00011 J
b0000111 L
#490000000
1!
b0000110001 &
1(
b0000110001 -
b00010 .
b01000 /
b00001 0
b00100 1
b10001 2
1;
b01000 =
1@
b10001 A
b00010 B
1E
b00001 F
b00001 G
b00100 J
b0001001 L
#500000000
0!
0(
0;
0@
0E
#510000000
1!
b0001001000 &
1(
b0001001000 -
b00001 .
b00100 /
b00010 0
b00010 1
b01000 2
b00000 4
1;
b00100 =
1@
b01000 A
b00001 B
1E
b00010 F
b00010 G
b00000 H
b00010 J
b0000101 L
#520000000
0!
0(
0;
0@
0E
#530000000
1!
b0000100100 &
1(
b0000100100 -
b00000 .
b10010 /
b00001 0
b00001 1
b00100 2
1;
b10010 =
1@
b00100 A
b00000 B
1E
b00001 F
b00001 G
b00001 J
b0000011 L
#540000000
0!
0(
0;
0@
0E
#550000000
1!
b0000010010 &
1(
b0000010010 -
b01001 /
b00000 0
b00000 1
b10010 2
1;
b01001 =
1@
b10010 A
1E
b00000 F
b00000 G
b00000 J
b0000001 L
#560000000
0!
0(
0;
0@
0E
#570000000
1!
b0000001001 &
1'
1(
1,
b0000001001 -
b00001 .
b10100 /
b00011 1
b01001 2
b00011 4
06
07
1;
b10100 =
0?
1@
b01001 A
b00001 B
0D
1E
b00011 H
b00011 J
b0000111 L
