ejercicios/Guia1/Ejercicio4/Fuentes/sumNb.vhd
library IEEE;
use IEEE.std_logic_1164.all;
use IEEE.numeric_std.all;


--sumador sin signo generico de N bits.
entity sumNb is
	generic( N: natural := 4);
	port(
		a_i: 	in std_logic_vector(N-1 downto 0);
		b_i: 	in std_logic_vector(N-1 downto 0);
		ci_i: 	in std_logic;
		s_o: 	out std_logic_vector(N-1 downto 0);
		co_o: 	out std_logic
	);
end;


architecture sumNb_arq of sumNb is
	signal res: std_logic_vector(N+1 downto 0);
begin
	res 	<= std_logic_vector(unsigned('0' & a_i & ci_i) + unsigned('0' & b_i & '1'));
	s_o		<= res(N downto 1);
	co_o 	<= res(N+1);
end sumNb_arq;

tps/tp6-final/Fuentes/regNb.vhd
library IEEE;
use IEEE.std_logic_1164.all;

entity regNb is
	generic(
		N: natural := 4
	);
	port(
		D_i:	in	std_logic_vector(N-1 downto 0);
		rst_i:	in	std_logic;
		ena_i:	in 	std_logic;
		clk_i:	in	std_logic;
		Q_o:	out	std_logic_vector(N-1 downto 0)
	);
end;


architecture regNb_arq of regNb is
begin
	process(clk_i, rst_i)
     	begin
          if rst_i = '1' then
               Q_o <= (others => '0');
          elsif rising_edge(clk_i) then
          	if ena_i = '1' then
                    Q_o <= D_i;
         	end if;
          end if;
     	end process;
end regNb_arq;

tps/tp6-final/multiplicador/Fuentes/multiplicador.vhd
library IEEE;
use IEEE.std_logic_1164.all;


entity multiplicador is
	generic(
		N: natural := 4
	);
	port(
		clk_i    : in std_logic;
		load_i   : in std_logic;
		opA_i    : in std_logic_vector(N-1 downto 0);
		opB_i    : in std_logic_vector(N-1 downto 0);
		product_o: out std_logic_vector(2*N-1 downto 0)
	);
end;

architecture multiplicador_arq of multiplicador is
	--declaracion del mponente registro
	component regNb is
		generic(
			N: natural := 4
		);
		port(
			D_i:	in	std_logic_vector(N-1 downto 0);
			rst_i:	in	std_logic;
			ena_i:	in 	std_logic;
			clk_i:	in	std_logic;
			Q_o:	out	std_logic_vector(N-1 downto 0)
		);
	end component;
	
	--declaracion del componente sumador
	component sumNb is
		generic( 
			N: natural := 4
		);
		port(
			a_i: 	in std_logic_vector(N-1 downto 0);
			b_i: 	in std_logic_vector(N-1 downto 0);
			ci_i: 	in std_logic;
			s_o: 	out std_logic_vector(N-1 downto 0);
			co_o: 	out std_logic
		);
	end component;
	signal entP,entB,salP,salSum,salB,salA,aux: std_logic_vector(N-1 downto 0);
	signal co: std_logic;
	signal enaRegP,enaRegB: std_logic;
begin
	process(clk_i,load_i) is
		variable counter: natural;
	begin
		if load_i = '1' then
			enaRegP <= '1';	
			enaRegB <= '1';
			counter := 0;
		elsif rising_edge(clk_i) then
			if counter = N-1  then
				enaRegP <= '0';
				enaRegB <= '0';
			else
				counter := counter + 1;
			end if;
		end if;
	end process;
	
	--instancia registro A
	regA_inst: regNb
		generic map(
			N => N		
		)
		port map(
			D_i   => opA_i,
			ena_i => '1',
			rst_i => '0',
			clk_i => clk_i,
			Q_o   => salA	
		);
		
	--instancia registro B
	regB_inst: regNb
		generic map(
			N => N
		)
		port map(
			D_i   => entB,
			ena_i => enaRegB,
			rst_i => '0',
			clk_i => clk_i,
			Q_o   => salB
		);
	--instancia registro P
	regP_inst: regNb
		generic map(
			N => N		
		)
		port map(
			D_i   => entP,
			ena_i => enaRegP,
			rst_i => load_i,
			clk_i => clk_i,
			Q_o   => salP
		);
		
	sum_inst: sumNb
		generic map(
			N => N		
		)
		port map(
			a_i  => salP,
			b_i  => aux,
			ci_i => '0',
			s_o  => salSum,
			co_o => co
		);
	entP <= co & salSum(N-1 downto 1);
	aux  <= salA  when salB(0) = '1' else (N-1 downto 0 => '0');
	entB <= opB_i when load_i = '1' else salSum(0) & salB(N-1 downto 1);
	product_o <= salP & salB; 
end multiplicador_arq;

tps/tp6-final/multiplicador/Fuentes/multiplicador_tb.vhd
library IEEE;
use IEEE.std_logic_1164.all;
use IEEE.numeric_std.all;


entity multiplicador_tb is
end;

architecture multiplicador_tb_arq of multiplicador_tb is
	component multiplicador is
		generic(
			N: natural := 4
		);
		port(
			clk_i    : in std_logic;
			load_i   : in std_logic;
			opA_i    : in std_logic_vector(N-1 downto 0);
			opB_i    : in std_logic_vector(N-1 downto 0);
			product_o: out std_logic_vector(2*N-1 downto 0)
		);
	end component;
	
	constant N_tb : natural := 5; 
	signal clk_tb : std_logic := '0';
	signal load_tb: std_logic := '0';
	signal rst_tb : std_logic := '1';
	signal opA_tb : std_logic_vector(N_tb-1 downto 0) := std_logic_vector(to_unsigned(3,N_tb));
	signal opB_tb : std_logic_vector(N_tb-1 downto 0) := std_logic_vector(to_unsigned(0,N_tb));
	signal product_tb: std_logic_vector(2*N_tb-1 downto 0);
begin
	clk_tb  <= not clk_tb after 10 ns;
	rst_tb  <= '0' after 20 ns;
 	
 	load_tb <= '1' after 100 ns, '0' after 120 ns,'1' after 460 ns, '0' after 480 ns;
	opB_tb  <= std_logic_vector(to_unsigned(6,N_tb)) after 100 ns,std_logic_vector(to_unsigned(2,N_tb)) after 460 ns;
	
	DUT: multiplicador
		generic map(
			N => N_tb
		)
		port map(
			clk_i     => clk_tb,
			load_i    => load_tb,
			opA_i     => opA_tb,
			opB_i     => opB_tb,
			product_o => product_tb
		);
end multiplicador_tb_arq;

tps/tp6-final/multiplicador/Simulacion/out/multiplicador_tb.vcd
$date
  Fri Jan  1 23:25:42 2021
$end
$version
  GHDL v0
$end
$timescale
  1 fs
$end
$scope module standard $end
$upscope $end
$scope module std_logic_1164 $end
$upscope $end
$scope module numeric_std $end
$upscope $end
$scope module multiplicador_tb $end
$var reg 1 ! clk_tb $end
$var reg 1 " load_tb $end
$var reg 1 # rst_tb $end
$var reg 5 $ opa_tb[4:0] $end
$var reg 5 % opb_tb[4:0] $end
$var reg 10 & product_tb[9:0] $end
$scope module dut $end
$var reg 1 ' clk_i $end
$var reg 1 ( load_i $end
$var reg 5 ) opa_i[4:0] $end
$var reg 5 * opb_i[4:0] $end
$var reg 10 + product_o[9:0] $end
$var reg 5 , entp[4:0] $end
$var reg 5 - entb[4:0] $end
$var reg 5 . salp[4:0] $end
$var reg 5 / salsum[4:0] $end
$var reg 5 0 salb[4:0] $end
$var reg 5 1 sala[4:0] $end
$var reg 5 2 aux[4:0] $end
$var reg 1 3 co $end
$var reg 1 4 enaregp $end
$var reg 1 5 enaregb $end
$scope module rega_inst $end
$var reg 5 6 d_i[4:0] $end
$var reg 1 7 rst_i $end
$var reg 1 8 ena_i $end
$var reg 1 9 clk_i $end
$var reg 5 : q_o[4:0] $end
$upscope $end
$scope module regb_inst $end
$var reg 5 ; d_i[4:0] $end
$var reg 1 < rst_i $end
$var reg 1 = ena_i $end
$var reg 1 > clk_i $end
$var reg 5 ? q_o[4:0] $end
$upscope $end
$scope module regp_inst $end
$var reg 5 @ d_i[4:0] $end
$var reg 1 A rst_i $end
$var reg 1 B ena_i $end
$var reg 1 C clk_i $end
$var reg 5 D q_o[4:0] $end
$upscope $end
$scope module sum_inst $end
$var reg 5 E a_i[4:0] $end
$var reg 5 F b_i[4:0] $end
$var reg 1 G ci_i $end
$var reg 5 H s_o[4:0] $end
$var reg 1 I co_o $end
$var reg 7 J res[6:0] $end
$upscope $end
$upscope $end
$upscope $end
$enddefinitions $end
#0
0!
0"
1#
b00011 $
b00000 %
bUUUUUUUUUU &
0'
0(
b00011 )
b00000 *
bUUUUUUUUUU +
bXXXXX ,
bXUUUU -
bUUUUU .
bXXXXX /
bUUUUU 0
bUUUUU 1
b00000 2
X3
U4
U5
b00011 6
07
18
09
bUUUUU :
bXUUUU ;
0<
U=
0>
bUUUUU ?
bXXXXX @
0A
UB
0C
bUUUUU D
bUUUUU E
b00000 F
0G
bXXXXX H
XI
bXXXXXXX J
#10000000
1!
1'
b00011 1
19
b00011 :
1>
1C
#20000000
0!
0#
0'
09
0>
0C
#30000000
1!
1'
19
1>
1C
#40000000
0!
0'
09
0>
0C
#50000000
1!
1'
19
1>
1C
#60000000
0!
0'
09
0>
0C
#70000000
1!
1'
19
1>
1C
#80000000
0!
0'
09
0>
0C
#90000000
1!
1'
04
05
19
0=
1>
0B
1C
#100000000
0!
1"
b00110 %
b00000UUUUU &
0'
1(
b00110 *
b00000UUUUU +
b00000 ,
b00110 -
b00000 .
b00000 /
03
14
15
09
b00110 ;
1=
0>
b00000 @
1A
1B
0C
b00000 D
b00000 E
b00000 H
0I
b0000001 J
#110000000
1!
b0000000110 &
1'
b0000000110 +
b00110 0
19
1>
b00110 ?
1C
#120000000
0!
0"
0'
0(
b00011 -
09
b00011 ;
0>
0A
0C
#130000000
1!
b0000000011 &
1'
b0000000011 +
b00001 ,
b10001 -
b00011 /
b00011 0
b00011 2
19
b10001 ;
1>
b00011 ?
b00001 @
1C
b00011 F
b00011 H
b0000111 J
#140000000
0!
0'
09
0>
0C
#150000000
1!
b0000110001 &
1'
b0000110001 +
b00010 ,
b01000 -
b00001 .
b00100 /
b10001 0
19
b01000 ;
1>
b10001 ?
b00010 @
1C
b00001 D
b00001 E
b00100 H
b0001001 J
#160000000
0!
0'
09
0>
0C
#170000000
1!
b0001001000 &
1'
b0001001000 +
b00001 ,
b00100 -
b00010 .
b00010 /
b01000 0
b00000 2
19
b00100 ;
1>
b01000 ?
b00001 @
1C
b00010 D
b00010 E
b00000 F
b00010 H
b0000101 J
#180000000
0!
0'
09
0>
0C
#190000000
1!
b0000100100 &
1'
b0000100100 +
b00000 ,
b10010 -
b00001 .
b00001 /
b00100 0
19
b10010 ;
1>
b00100 ?
b00000 @
1C
b00001 D
b00001 E
b00001 H
b0000011 J
#200000000
0!
0'
09
0>
0C
#210000000
1!
b0000010010 &
1'
b0000010010 +
b01001 -
b00000 .
b00000 /
b10010 0
04
05
19
b01001 ;
0=
1>
b10010 ?
0B
1C
b00000 D
b00000 E
b00000 H
b0000001 J
#220000000
0!
0'
09
0>
0C
#230000000
1!
1'
19
1>
1C
#240000000
0!
0'
09
0>
0C
#250000000
1!
1'
19
1>
1C
#260000000
0!
0'
09
0>
0C
#270000000
1!
1'
19
1>
1C
#280000000
0!
0'
09
0>
0C
#290000000
1!
1'
19
1>
1C
#300000000
0!
0'
09
0>
0C
#310000000
1!
1'
19
1>
1C
#320000000
0!
0'
09
0>
0C
#330000000
1!
1'
19
1>
1C
#340000000
0!
0'
09
0>
0C
#350000000
1!
1'
19
1>
1C
#360000000
0!
0'
09
0>
0C
#370000000
1!
1'
19
1>
1C
#380000000
0!
0'
09
0>
0C
#390000000
1!
1'
19
1>
1C
#400000000
0!
0'
09
0>
0C
#410000000
1!
1'
19
1>
1C
#420000000
0!
0'
09
0>
0C
#430000000
1!
1'
19
1>
1C
#440000000
0!
0'
09
0>
0C
#450000000
1!
1'
19
1>
1C
#460000000
0!
1"
b00010 %
0'
1(
b00010 *
b00010 -
14
15
09
b00010 ;
1=
0>
1A
1B
0C
#470000000
1!
b0000000010 &
1'
b0000000010 +
b00010 0
19
1>
b00010 ?
1C
#480000000
0!
0"
0'
0(
b00001 -
09
b00001 ;
0>
0A
0C
#490000000
1!
b0000000001 &
1'
b0000000001 +
b00001 ,
b10000 -
b00011 /
b00001 0
b00011 2
19
b10000 ;
1>
b00001 ?
b00001 @
1C
b00011 F
b00011 H
b0000111 J
#500000000
0!
0'
09
0>
0C
#510000000
1!
b0000110000 &
1'
b0000110000 +
b00000 ,
b11000 -
b00001 .
b00001 /
b10000 0
b00000 2
19
b11000 ;
1>
b10000 ?
b00000 @
1C
b00001 D
b00001 E
b00000 F
b00001 H
b0000011 J
#520000000
0!
0'
09
0>
0C
#530000000
1!
b0000011000 &
1'
b0000011000 +
b01100 -
b00000 .
b00000 /
b11000 0
19
b01100 ;
1>
b11000 ?
1C
b00000 D
b00000 E
b00000 H
b0000001 J
#540000000
0!
0'
09
0>
0C
#550000000
1!
b0000001100 &
1'
b0000001100 +
b00110 -
b01100 0
19
b00110 ;
1>
b01100 ?
1C
#560000000
0!
0'
09
0>
0C
#570000000
1!
b0000000110 &
1'
b0000000110 +
b00011 -
b00110 0
04
05
19
b00011 ;
0=
1>
b00110 ?
0B
1C
